{"rf_test_mean_r2":0.8061,"rf_val_mean_r2":0.8141,"clf_accuracy":0.68,"clf_macro_f1":0.6739,"clf_macro_precision":0.672,"clf_macro_recall":0.68,"clf_roc_auc_macro":0.8689,"best_params":"{'n_estimators': 200, 'max_features': 'sqrt', 'min_samples_split': 2}","n_cv_folds":5,"per_label":{"sleep_efficiency":{"display":"Sleep Efficiency","test_r2":0.8697,"test_mae":0.0383,"test_rmse":0.0462,"cv_r2_mean":0.8431,"cv_r2_std":0.0298},"sleep_duration_h":{"display":"Sleep Duration","test_r2":0.8071,"test_mae":0.3608,"test_rmse":0.4438,"cv_r2_mean":0.7661,"cv_r2_std":0.0472},"awakenings":{"display":"Awakenings","test_r2":0.7499,"test_mae":0.6315,"test_rmse":0.747,"cv_r2_mean":0.7377,"cv_r2_std":0.0314},"sleep_score":{"display":"Sleep Score","test_r2":0.7979,"test_mae":3.912,"test_rmse":4.872,"cv_r2_mean":0.7559,"cv_r2_std":0.044}},"ridge_mean_r2":0.7971,"mean_baseline_r2":-0.001}